<?xml version="1.0" encoding="utf-8" ?>
<Defs>

  <PawnKindDef ParentName="OutlanderBase">
    <defName>ABY_HexgunThrall</defName>
    <label>hexgun thrall</label>
    <race>ABY_HexgunThrall</race>
    <defaultFactionType>ABY_AbyssalHost</defaultFactionType>
    <combatPower>210</combatPower>
    <ecoSystemWeight>0</ecoSystemWeight>
    <canArriveManhunter>false</canArriveManhunter>
    <apparelMoney Inherit="False">0</apparelMoney>
    <weaponMoney Inherit="False">720</weaponMoney>
    <weaponTags Inherit="False">
      <li>ABY_HexgunWeapon</li>
    </weaponTags>
    <apparelRequired Inherit="False" />
    <apparelTags Inherit="False" />
    <apparelIgnoreSeasons>true</apparelIgnoreSeasons>
    <forceNormalGearQuality>true</forceNormalGearQuality>
    <gearHealthRange>1~1</gearHealthRange>
  </PawnKindDef>

</Defs>
